{"sections":{"main":{"type":"main-page","disabled":true,"settings":{"padding_top":28,"padding_bottom":28}},"dd_featured_categories_FzgtTU":{"type":"dd-featured-categories","blocks":{"category_mcgjiU":{"type":"category","settings":{"title":"Bundles","image":"shopify:\/\/shop_images\/bundles_27a43149-174d-4a86-bb7f-d1fb13ae2bdd.png","hover_image":"shopify:\/\/shop_images\/SC3PRO-1.webp","link":"shopify:\/\/collections\/bundles"}},"category_Upgn3h":{"type":"category","settings":{"title":"Frames and cockpits","image":"shopify:\/\/shop_images\/TR120S-BLKe02-min_1080x_0bdee62b-08a5-42b8-996e-ff3b8fc92564.webp","hover_image":"shopify:\/\/shop_images\/CopyofTR120S-BLKOA-PF-NS_03-INCLUDED_1080x_ac52b547-6b46-4cab-90fe-6620a193269b.webp","link":"shopify:\/\/collections\/simulator-frames-and-cockipts"}},"category_HeQiMn":{"type":"category","settings":{"title":"Monitor Mounts","image":"shopify:\/\/shop_images\/KIT-TR80SMLSINCM2-BLK2_2_1080x_0293dca7-0e1b-4a1f-a0b3-1d39beb642eb.webp","hover_image":"shopify:\/\/shop_images\/KIT-TR80SMLSINCM2-BLK2_5_1080x_1bb51e08-b70f-4d49-a90f-c50255994322.webp","link":"shopify:\/\/collections\/monitor-stands"}},"category_Arn9zq":{"type":"category","settings":{"title":"Seats & Add-ons","image":"shopify:\/\/shop_images\/SA-11-UPDATE_02_2_1080x_0247828c-c919-41e0-82e2-17b951859c62.webp","hover_image":"shopify:\/\/shop_images\/SEAT-5.2_1080x_484cae6e-e452-4941-bc64-577ceb82a43c.webp","link":"shopify:\/\/collections\/seats-seats-accessories"}},"category_N8YUme":{"type":"category","settings":{"title":"Wheel base","image":"shopify:\/\/shop_images\/SC3PRO-1.webp","hover_image":"shopify:\/\/shop_images\/SC3PRO-1.webp","link":"shopify:\/\/collections\/wheelbase"}},"category_LCAAgJ":{"type":"category","settings":{"title":"Wheels","image":"shopify:\/\/shop_images\/DSC3853__-1-1-square.png","hover_image":"shopify:\/\/shop_images\/Valo_Product_Take1-1-1-square.png","link":"shopify:\/\/collections\/wheels"}},"category_8CP8pe":{"type":"category","settings":{"title":"Pedals","image":"shopify:\/\/shop_images\/DSC0846_1_-1-1-square.png","hover_image":"shopify:\/\/shop_images\/DSC0846-3-2-rectangle.png","link":"shopify:\/\/collections\/pedals"}},"category_Yw8qjq":{"type":"category","settings":{"title":"Accessories","image":"shopify:\/\/shop_images\/Conspit_CSD_dashboard.png","hover_image":"shopify:\/\/shop_images\/2_1_copy.png","link":"shopify:\/\/collections\/accessories"}},"category_aRRHix":{"type":"category","settings":{"title":"GAMING PC \/ Monitors","image":"shopify:\/\/shop_images\/2-1.avif","link":"shopify:\/\/collections\/monitors-computers"}},"category_hzD6xV":{"type":"category","settings":{"title":"Motion & Haptic systems","image":"shopify:\/\/shop_images\/motion_haptics.png","link":"shopify:\/\/collections\/motion-haptic-systems"}}},"block_order":["category_mcgjiU","category_Upgn3h","category_HeQiMn","category_Arn9zq","category_N8YUme","category_LCAAgJ","category_8CP8pe","category_Yw8qjq","category_aRRHix","category_hzD6xV"],"name":"Featured Categories","settings":{"title":"Sim PRODUCTS"}}},"order":["main","dd_featured_categories_FzgtTU"]}